launcherp/.DS_Store
launcherp/__main__.py
launcherp/assets/.DS_Store
launcherp/assets/back.png
launcherp/assets/black.png
launcherp/assets/mainIcon.png
launcherp/assets/morpionIcon.png
launcherp/assets/pythonLogo.png
launcherp-0.1.7.dist-info/WHEEL
launcherp-0.1.7.dist-info/METADATA
launcherp-0.1.7.dist-info/RECORD
